caniusethat/__init__.py
caniusethat/_logging.py
caniusethat/_thread.py
caniusethat/_types.py
caniusethat/cli.py
caniusethat/py.typed
caniusethat/rpc_utils.py
caniusethat/shareable.py
caniusethat/thing.py
caniusethat-0.4.1.dist-info/LICENSE
caniusethat-0.4.1.dist-info/METADATA
caniusethat-0.4.1.dist-info/WHEEL
caniusethat-0.4.1.dist-info/entry_points.txt
caniusethat-0.4.1.dist-info/top_level.txt
caniusethat-0.4.1.dist-info/RECORD
